ipctk.cpython-39-x86_64-linux-gnu.so
ipc/collision_mesh.cpp
ipc/ipc.cpp
ipc/ipc.hpp
ipc/CMakeLists.txt
ipc/collision_mesh.hpp
ipc/barrier/adaptive_stiffness.hpp
ipc/barrier/adaptive_stiffness.cpp
ipc/barrier/barrier.hpp
ipc/barrier/CMakeLists.txt
ipc/barrier/barrier.cpp
ipc/broad_phase/broad_phase.cpp
ipc/broad_phase/aabb.cpp
ipc/broad_phase/bvh.hpp
ipc/broad_phase/brute_force.cpp
ipc/broad_phase/sweep_and_tiniest_queue.hpp
ipc/broad_phase/voxel_size_heuristic.cpp
ipc/broad_phase/voxel_size_heuristic.hpp
ipc/broad_phase/hash_grid.cpp
ipc/broad_phase/sweep_and_tiniest_queue.cpp
ipc/broad_phase/hash_grid.hpp
ipc/broad_phase/broad_phase.hpp
ipc/broad_phase/spatial_hash.cpp
ipc/broad_phase/CMakeLists.txt
ipc/broad_phase/sweep_and_prune.cpp
ipc/broad_phase/aabb.hpp
ipc/broad_phase/brute_force.hpp
ipc/broad_phase/sweep_and_prune.hpp
ipc/broad_phase/bvh.cpp
ipc/broad_phase/spatial_hash.hpp
ipc/ccd/inexact_ccd.cpp
ipc/ccd/aabb.cpp
ipc/ccd/nonlinear_ccd.cpp
ipc/ccd/inexact_point_edge.hpp
ipc/ccd/tight_inclusion_ccd.hpp
ipc/ccd/check_initial_distance.hpp
ipc/ccd/additive_ccd.hpp
ipc/ccd/additive_ccd.cpp
ipc/ccd/inexact_point_edge.cpp
ipc/ccd/point_static_plane.hpp
ipc/ccd/default_narrow_phase_ccd.hpp
ipc/ccd/inexact_ccd.hpp
ipc/ccd/CMakeLists.txt
ipc/ccd/narrow_phase_ccd.hpp
ipc/ccd/aabb.hpp
ipc/ccd/nonlinear_ccd.hpp
ipc/ccd/tight_inclusion_ccd.cpp
ipc/ccd/point_static_plane.cpp
ipc/candidates/candidates.hpp
ipc/candidates/face_vertex.hpp
ipc/candidates/collision_stencil.hpp
ipc/candidates/face_face.hpp
ipc/candidates/edge_face.hpp
ipc/candidates/edge_vertex.cpp
ipc/candidates/face_face.cpp
ipc/candidates/edge_vertex.hpp
ipc/candidates/edge_edge.cpp
ipc/candidates/vertex_vertex.hpp
ipc/candidates/edge_face.cpp
ipc/candidates/candidates.cpp
ipc/candidates/continuous_collision_candidate.cpp
ipc/candidates/CMakeLists.txt
ipc/candidates/edge_edge.hpp
ipc/candidates/vertex_vertex.cpp
ipctk-1.3.1.dist-info/top_level.txt
ipctk-1.3.1.dist-info/RECORD
ipctk-1.3.1.dist-info/LICENSE
ipctk-1.3.1.dist-info/METADATA
ipctk-1.3.1.dist-info/WHEEL
