Metadata-Version: 2.1
Name: ipctk
Version: 1.3.1
Summary: A set of reusable functions to integrate Incremental Potential Contact (IPC) into a simulation.
Author-email: Zachary Ferguson <zy.fergus@gmail.edu>
License: MIT License
Project-URL: Homepage, https://ipctk.xyz
Project-URL: Bug Tracker, https://github.com/ipc-sim/ipc-toolkit/issues
Project-URL: Source Code, https://github.com/ipc-sim/ipc-toolkit
Keywords: IPC,simulation,physics,science,research
Classifier: Programming Language :: C++
Classifier: Programming Language :: Python :: 3
Classifier: Topic :: Games/Entertainment :: Simulation
Classifier: Topic :: Scientific/Engineering :: Physics
Classifier: License :: OSI Approved :: MIT License
Classifier: Operating System :: OS Independent
Classifier: Intended Audience :: Science/Research
Requires-Python: >=3.6
License-File: LICENSE
Requires-Dist: numpy
Requires-Dist: scipy
